README.rst
setup.py
TMCL/__init__.py
TMCL/bus.py
TMCL/commands.py
TMCL/motor.py
TMCL/reply.py
TMCL.egg-info/PKG-INFO
TMCL.egg-info/SOURCES.txt
TMCL.egg-info/dependency_links.txt
TMCL.egg-info/not-zip-safe
TMCL.egg-info/requires.txt
TMCL.egg-info/top_level.txt
tmcl/__init__.py
tmcl/bus.py
tmcl/commands.py
tmcl/motor.py
tmcl/reply.py
tmcl.egg-info/PKG-INFO
tmcl.egg-info/SOURCES.txt
tmcl.egg-info/dependency_links.txt
tmcl.egg-info/not-zip-safe
tmcl.egg-info/requires.txt
tmcl.egg-info/top_level.txt