Metadata-Version: 1.0
Name: TMCL
Version: 1.0
Summary: Talk to Trinamic Stepper Motors using TMCL over serial
Home-page: https://github.com/NativeDesign/python-tmcl
Author: Alan Pich
Author-email: alanp@native.com
License: MIT
Platform: UNKNOWN
